ece_calculator/__init__.py
ece_calculator/ece.py
ece_calculator-0.1.0.dist-info/METADATA
ece_calculator-0.1.0.dist-info/WHEEL
ece_calculator-0.1.0.dist-info/RECORD
