Metadata-Version: 2.4
Name: ece-calculator
Version: 0.1.0
Summary: Calculate Expected Calibration Error (ECE) from model predictions
Keywords: ECE,uncertainty,calibration,machine learning
Author: Kaylee Smith
Requires-Python: >=3.11,<4.0
Classifier: Programming Language :: Python :: 3
Classifier: Programming Language :: Python :: 3.11
Classifier: Programming Language :: Python :: 3.12
Classifier: Programming Language :: Python :: 3.13
Classifier: Programming Language :: Python :: 3.14
Requires-Dist: numpy (>=2.3.3,<3.0.0)
Requires-Dist: scikit-learn (>=1.7.2,<2.0.0)
Requires-Dist: scipy (>=1.16.2,<2.0.0)
Requires-Dist: tensorflow (>=2.20.0,<3.0.0)
